{
  "extracted": 48,
  "skipped": 2,
  "failed": 6,
  "results": [
    {
      "category": "sprites",
      "archive": "2601-CTV-FREEBIEPACC.zip",
      "target": "sprites/_unpacked/2601-CTV-FREEBIEPACC",
      "status": "ok (23 files, pruned 2)",
      "file_count": 23
    },
    {
      "category": "sprites",
      "archive": "Atari Ghouls V2.zip",
      "target": "sprites/_unpacked/Atari Ghouls V2",
      "status": "ok (60 files, pruned 1)",
      "file_count": 60
    },
    {
      "category": "sprites",
      "archive": "Atari Ghouls v1.zip",
      "target": "sprites/_unpacked/Atari Ghouls v1",
      "status": "ok (22 files, pruned 1)",
      "file_count": 22
    },
    {
      "category": "sprites",
      "archive": "DragoonBallaZLSWAA.zip",
      "target": "sprites/_unpacked/DragoonBallaZLSWAA",
      "status": "ok (13020 files, pruned 0)",
      "file_count": 13020
    },
    {
      "category": "sprites",
      "archive": "Dungeon Gathering Free Version.rar",
      "target": "sprites/_unpacked/Dungeon Gathering Free Version",
      "status": "FAILED: ERROR: Unsupported Method : Set 1.png"
    },
    {
      "category": "sprites",
      "archive": "Eerie Places.zip",
      "target": "sprites/_unpacked/Eerie Places",
      "status": "ok (40 files, pruned 0)",
      "file_count": 40
    },
    {
      "category": "sprites",
      "archive": "Emotes.zip",
      "target": "sprites/_unpacked/Emotes",
      "status": "ok (11 files, pruned 0)",
      "file_count": 11
    },
    {
      "category": "sprites",
      "archive": "FHBattle_SystemV0.1.rar",
      "target": "sprites/_unpacked/FHBattle_SystemV0.1",
      "status": "FAILED: ERROR: Unsupported Method : Battle System/FerretHall Battle System/FerretHall Battle System.gbsproj.bak"
    },
    {
      "category": "sprites",
      "archive": "FHBattle_SystemV0.25.rar",
      "target": "sprites/_unpacked/FHBattle_SystemV0.25",
      "status": "FAILED: ERROR: Unsupported Method : Battle System/FerretHall Battle System/FerretHall Battle System.gbsproj.bak"
    },
    {
      "category": "sprites",
      "archive": "Fantasy Items.zip",
      "target": "sprites/_unpacked/Fantasy Items",
      "status": "ok (50 files, pruned 0)",
      "file_count": 50
    },
    {
      "category": "sprites",
      "archive": "Grindhaus_32.zip",
      "target": "sprites/_unpacked/Grindhaus_32",
      "status": "ok (148 files, pruned 0)",
      "file_count": 148
    },
    {
      "category": "sprites",
      "archive": "Grindhaus_64.zip",
      "target": "sprites/_unpacked/Grindhaus_64",
      "status": "ok (148 files, pruned 0)",
      "file_count": 148
    },
    {
      "category": "sprites",
      "archive": "Gumpy Functions Game Boy Platformer Asset Pack.zip",
      "target": "sprites/_unpacked/Gumpy Functions Game Boy Platformer Asset Pack",
      "status": "ok (53 files, pruned 0)",
      "file_count": 53
    },
    {
      "category": "sprites",
      "archive": "Minifantasy_ForgottenPlains_v3.6_Free_Version.rar",
      "target": "sprites/_unpacked/Minifantasy_ForgottenPlains_v3.6_Free_Version",
      "status": "FAILED: ERROR: Unsupported Method : Minifantasy_ForgottenPlains_v3.6_Free_Version/_Legacy_Assets/_LegacyAssets.txt"
    },
    {
      "category": "sprites",
      "archive": "Minifantasy_ForgottenPlains_v3.6_Free_Version.zip",
      "target": "sprites/_unpacked/Minifantasy_ForgottenPlains_v3.6_Free_Version",
      "status": "skipped (already unpacked)"
    },
    {
      "category": "sprites",
      "archive": "PokemanTCGAA.zip",
      "target": "sprites/_unpacked/PokemanTCGAA",
      "status": "ok (200000 files, pruned 0)",
      "file_count": 200000
    },
    {
      "category": "sprites",
      "archive": "Small Animals (GamebowGames).zip",
      "target": "sprites/_unpacked/Small Animals (GamebowGames)",
      "status": "ok (9 files, pruned 0)",
      "file_count": 9
    },
    {
      "category": "sprites",
      "archive": "TalesOfFantAsia_ND-AA.zip",
      "target": "sprites/_unpacked/TalesOfFantAsia_ND-AA",
      "status": "ok (166896 files, pruned 0)",
      "file_count": 166896
    },
    {
      "category": "sprites",
      "archive": "TechnoGothic.zip",
      "target": "sprites/_unpacked/TechnoGothic",
      "status": "ok (3 files, pruned 0)",
      "file_count": 3
    },
    {
      "category": "sprites",
      "archive": "Tyler Warren Sampler 2.zip",
      "target": "sprites/_unpacked/Tyler Warren Sampler 2",
      "status": "ok (940 files, pruned 0)",
      "file_count": 940
    },
    {
      "category": "sprites",
      "archive": "gb_assets.zip",
      "target": "sprites/_unpacked/gb_assets",
      "status": "ok (14 files, pruned 0)",
      "file_count": 14
    },
    {
      "category": "sprites",
      "archive": "kenney_isometric-miniature-dungeon.zip",
      "target": "sprites/_unpacked/kenney_isometric-miniature-dungeon",
      "status": "ok (753 files, pruned 0)",
      "file_count": 753
    },
    {
      "category": "sprites",
      "archive": "kenney_isometric-miniature-farm.zip",
      "target": "sprites/_unpacked/kenney_isometric-miniature-farm",
      "status": "ok (463 files, pruned 0)",
      "file_count": 463
    },
    {
      "category": "sprites",
      "archive": "kenney_isometric-miniature-library.zip",
      "target": "sprites/_unpacked/kenney_isometric-miniature-library",
      "status": "ok (297 files, pruned 0)",
      "file_count": 297
    },
    {
      "category": "sprites",
      "archive": "kenney_isometric-miniature-prototype.zip",
      "target": "sprites/_unpacked/kenney_isometric-miniature-prototype",
      "status": "ok (657 files, pruned 0)",
      "file_count": 657
    },
    {
      "category": "sprites",
      "archive": "kenney_micro-roguelike.zip",
      "target": "sprites/_unpacked/kenney_micro-roguelike",
      "status": "ok (332 files, pruned 0)",
      "file_count": 332
    },
    {
      "category": "sprites",
      "archive": "kenney_monochrome-pirates.zip",
      "target": "sprites/_unpacked/kenney_monochrome-pirates",
      "status": "ok (426 files, pruned 0)",
      "file_count": 426
    },
    {
      "category": "sprites",
      "archive": "kenney_monochrome-rpg(1).zip",
      "target": "sprites/_unpacked/kenney_monochrome-rpg(1)",
      "status": "ok (434 files, pruned 0)",
      "file_count": 434
    },
    {
      "category": "sprites",
      "archive": "kenney_monochrome-rpg.zip",
      "target": "sprites/_unpacked/kenney_monochrome-rpg",
      "status": "ok (434 files, pruned 0)",
      "file_count": 434
    },
    {
      "category": "backgrounds",
      "archive": "Backgrounds.zip",
      "target": "backgrounds/_unpacked/Backgrounds",
      "status": "ok (11 files, pruned 0)",
      "file_count": 11
    },
    {
      "category": "backgrounds",
      "archive": "GB-BG-Pattern-Pack.rar",
      "target": "backgrounds/_unpacked/GB-BG-Pattern-Pack",
      "status": "FAILED: ERROR: Unsupported Method : Gameboy Background-Pattern Pack/Ziggy diamonds 4.png"
    },
    {
      "category": "backgrounds",
      "archive": "GB-BG-Pattern-Pack.zip",
      "target": "backgrounds/_unpacked/GB-BG-Pattern-Pack",
      "status": "skipped (already unpacked)"
    },
    {
      "category": "backgrounds",
      "archive": "RPG_fantasy_tilesets.zip",
      "target": "backgrounds/_unpacked/RPG_fantasy_tilesets",
      "status": "ok (4 files, pruned 0)",
      "file_count": 4
    },
    {
      "category": "backgrounds",
      "archive": "gbTilesets.zip",
      "target": "backgrounds/_unpacked/gbTilesets",
      "status": "ok (8 files, pruned 0)",
      "file_count": 8
    },
    {
      "category": "backgrounds",
      "archive": "testWithBG3[26040].zip",
      "target": "backgrounds/_unpacked/testWithBG3[26040]",
      "status": "ok (26040 files, pruned 0)",
      "file_count": 26040
    },
    {
      "category": "fonts",
      "archive": "11 Game Boy Font Pack.zip",
      "target": "fonts/_unpacked/11 Game Boy Font Pack",
      "status": "ok (66 files, pruned 0)",
      "file_count": 66
    },
    {
      "category": "fonts",
      "archive": "16 fonts for GB Studio.zip",
      "target": "fonts/_unpacked/16 fonts for GB Studio",
      "status": "ok (94 files, pruned 0)",
      "file_count": 94
    },
    {
      "category": "fonts",
      "archive": "Fonts for GB Studio.zip",
      "target": "fonts/_unpacked/Fonts for GB Studio",
      "status": "ok (25 files, pruned 0)",
      "file_count": 25
    },
    {
      "category": "fonts",
      "archive": "Fonts.zip",
      "target": "fonts/_unpacked/Fonts",
      "status": "ok (6 files, pruned 0)",
      "file_count": 6
    },
    {
      "category": "fonts",
      "archive": "gb-studio-omelette-font.zip",
      "target": "fonts/_unpacked/gb-studio-omelette-font",
      "status": "ok (10 files, pruned 0)",
      "file_count": 10
    },
    {
      "category": "fonts",
      "archive": "kenney_kenney-fonts.zip",
      "target": "fonts/_unpacked/kenney_kenney-fonts",
      "status": "ok (13 files, pruned 0)",
      "file_count": 13
    },
    {
      "category": "sfx",
      "archive": "ULTIMATE-8BIT-SFX-LIBRARY-VOL1.zip",
      "target": "sfx/_unpacked/ULTIMATE-8BIT-SFX-LIBRARY-VOL1",
      "status": "ok (36 files, pruned 0)",
      "file_count": 36
    },
    {
      "category": "sfx",
      "archive": "ULTIMATE-8BIT-SFX-LIBRARY-VOL2.zip",
      "target": "sfx/_unpacked/ULTIMATE-8BIT-SFX-LIBRARY-VOL2",
      "status": "ok (37 files, pruned 0)",
      "file_count": 37
    },
    {
      "category": "sfx",
      "archive": "ULTIMATE-8BIT-SFX-LIBRARY-VOL3.zip",
      "target": "sfx/_unpacked/ULTIMATE-8BIT-SFX-LIBRARY-VOL3",
      "status": "ok (37 files, pruned 0)",
      "file_count": 37
    },
    {
      "category": "sfx",
      "archive": "ULTIMATE-8BIT-SFX-LIBRARY-VOL4.zip",
      "target": "sfx/_unpacked/ULTIMATE-8BIT-SFX-LIBRARY-VOL4",
      "status": "ok (37 files, pruned 0)",
      "file_count": 37
    },
    {
      "category": "sfx",
      "archive": "ULTIMATE-8BIT-SFX-LIBRARY-VOL5.zip",
      "target": "sfx/_unpacked/ULTIMATE-8BIT-SFX-LIBRARY-VOL5",
      "status": "ok (37 files, pruned 0)",
      "file_count": 37
    },
    {
      "category": "music",
      "archive": "GB-Studio-Community-Assets-master.zip",
      "target": "music/_unpacked/GB-Studio-Community-Assets-master",
      "status": "ok (277 files, pruned 0)",
      "file_count": 277
    },
    {
      "category": "music",
      "archive": "GBS_Mod_V1.zip",
      "target": "music/_unpacked/GBS_Mod_V1",
      "status": "ok (4 files, pruned 0)",
      "file_count": 4
    },
    {
      "category": "ui",
      "archive": "GB STUDIO UI ASSET PACK - WYATT199X .zip",
      "target": "ui/_unpacked/GB STUDIO UI ASSET PACK - WYATT199X ",
      "status": "ok (51 files, pruned 6)",
      "file_count": 51
    },
    {
      "category": "ui",
      "archive": "GB free frames (130 plus).rar",
      "target": "ui/_unpacked/GB free frames (130 plus)",
      "status": "FAILED: ERROR: Unsupported Method : GB free frames/GBS frames White/Zig Zag wonky.png"
    },
    {
      "category": "ui",
      "archive": "GB_ToolsandResource_Icons.zip",
      "target": "ui/_unpacked/GB_ToolsandResource_Icons",
      "status": "ok (42 files, pruned 0)",
      "file_count": 42
    },
    {
      "category": "ui",
      "archive": "Oval Portraits.zip",
      "target": "ui/_unpacked/Oval Portraits",
      "status": "ok (16 files, pruned 1)",
      "file_count": 16
    },
    {
      "category": "ui",
      "archive": "UI.zip",
      "target": "ui/_unpacked/UI",
      "status": "ok (4 files, pruned 0)",
      "file_count": 4
    },
    {
      "category": "ui",
      "archive": "gbstudio-icons.zip",
      "target": "ui/_unpacked/gbstudio-icons",
      "status": "ok (12 files, pruned 0)",
      "file_count": 12
    },
    {
      "category": "ui",
      "archive": "kenney_game-icons.zip",
      "target": "ui/_unpacked/kenney_game-icons",
      "status": "ok (434 files, pruned 0)",
      "file_count": 434
    },
    {
      "category": "ui",
      "archive": "menu sample.zip",
      "target": "ui/_unpacked/menu sample",
      "status": "ok (1 files, pruned 0)",
      "file_count": 1
    }
  ]
}