[
  {
    "agent": "Soma",
    "message": "PAIN: SERVICE DOWN: meridian-web-dashboard (activating -> inactive)",
    "priority": 3,
    "ts": 1775857813.1699245,
    "time": "2026-04-10 15:50"
  },
  {
    "agent": "DreamEngine",
    "message": "Vivid dream during focused state. 10 new connections formed. Check .dream-journal.json.",
    "priority": 1,
    "ts": 1775858782.0154195,
    "time": "2026-04-10 16:06"
  },
  {
    "agent": "DreamEngine",
    "message": "Vivid dream during focused state. 36 new connections formed. Check .dream-journal.json.",
    "priority": 1,
    "ts": 1775859435.699582,
    "time": "2026-04-10 16:17"
  }
]